tf_common-1.0.0.dist-info/METADATA
tf_common-1.0.0.dist-info/RECORD
tf_common-1.0.0.dist-info/WHEEL
tf_common-1.0.0.dist-info/top_level.txt
tf_common-1.0.0.dist-info/zip-safe
tfcommon/__init__.py
