Metadata-Version: 2.1
Name: tf-common
Version: 1.0.0
Summary: A common liberary of tensorflow
Home-page: https://github.com/terryyrliang
Author: Terry
Author-email: 335208143@qq.com
License: MIT
Platform: UNKNOWN
Classifier: License :: OSI Approved :: MIT License
Classifier: Operating System :: OS Independent
Classifier: Programming Language :: Python :: 3
Requires-Dist: tensorflow (>=1.7.0)
Requires-Dist: numpy (>=1.14.3)
